tank/__init__.py
tank/bootstrap.py
tank/install-terraform.sh
tank/main.py
tank/controllers/__init__.py
tank/controllers/ansible.py
tank/controllers/base.py
tank/controllers/cluster.py
tank/core/__init__.py
tank/core/exc.py
tank/core/version.py
tank/ext/__init__.py
tank/plugins/__init__.py
tank/providers/digitalocean/backend.tf
tank/providers/digitalocean/main.tf
tank/providers/digitalocean/vars.sh
tank/providers/gce/backend.tf
tank/providers/gce/main.tf
tank/providers/gce/vars.sh
tank/templates/requirements.yml
tank/tools/ansible/ansible-requirements.yml
tank/tools/ansible/ansible.cfg
tank/tools/ansible/play.yml
tank_polkadot-0.1.0.dist-info/LICENSE
tank_polkadot-0.1.0.dist-info/METADATA
tank_polkadot-0.1.0.dist-info/WHEEL
tank_polkadot-0.1.0.dist-info/entry_points.txt
tank_polkadot-0.1.0.dist-info/top_level.txt
tank_polkadot-0.1.0.dist-info/RECORD
